pyviz/.version
pyviz/__init__.py
pyviz/__main__.py
pyviz/examples/datasets.yml
pyviz/examples/environment.yml
pyviz/examples/assets/PyViz_logo_wm.png
pyviz/examples/assets/PyViz_logo_wm_line.png
pyviz/examples/assets/altair.png
pyviz/examples/assets/bokeh.png
pyviz/examples/assets/bokeh_logo.svg
pyviz/examples/assets/cartopy.png
pyviz/examples/assets/colorcet.png
pyviz/examples/assets/dask.png
pyviz/examples/assets/dask.svg
pyviz/examples/assets/datashader.png
pyviz/examples/assets/datashader_pipeline.png
pyviz/examples/assets/ds_hv_bokeh.png
pyviz/examples/assets/ds_hv_bokeh2.png
pyviz/examples/assets/geopandas.png
pyviz/examples/assets/geoviews.png
pyviz/examples/assets/ggplot2.png
pyviz/examples/assets/graphviz.png
pyviz/examples/assets/header_logo.png
pyviz/examples/assets/holoviews.png
pyviz/examples/assets/hv+bk.png
pyviz/examples/assets/hv_gv_bk_ds_pa.png
pyviz/examples/assets/hvplot.png
pyviz/examples/assets/intake.png
pyviz/examples/assets/iris.png
pyviz/examples/assets/jupyter.png
pyviz/examples/assets/landscape_hv_nx.png
pyviz/examples/assets/landscape_hv_nx_pyviz.png
pyviz/examples/assets/matplotlib_logo.png
pyviz/examples/assets/matplotlib_wm.png
pyviz/examples/assets/networkx.png
pyviz/examples/assets/numba.png
pyviz/examples/assets/numpy.png
pyviz/examples/assets/pandas.png
pyviz/examples/assets/panel.png
pyviz/examples/assets/param.png
pyviz/examples/assets/pillow.png
pyviz/examples/assets/plotly.png
pyviz/examples/assets/plotnine.png
pyviz/examples/assets/scipy.png
pyviz/examples/assets/seaborn.png
pyviz/examples/assets/shortcuts.png
pyviz/examples/assets/sympy.png
pyviz/examples/assets/tutorial_app.gif
pyviz/examples/assets/vega.png
pyviz/examples/assets/workflow.png
pyviz/examples/assets/xarray.png
pyviz/examples/assets/xarray_wm.png
pyviz/examples/assets/yt.png
pyviz/examples/assets/images/dask.svg
pyviz/examples/assets/images/datashader.png
pyviz/examples/assets/images/holoviews.png
pyviz/examples/assets/images/numba.jpg
pyviz-0.10.3.dist-info/LICENSE.txt
pyviz-0.10.3.dist-info/METADATA
pyviz-0.10.3.dist-info/WHEEL
pyviz-0.10.3.dist-info/entry_points.txt
pyviz-0.10.3.dist-info/top_level.txt
pyviz-0.10.3.dist-info/RECORD
