Metadata-Version: 2.1
Name: pyviz
Version: 0.10.3
Summary: How to solve visualization problems with Python tools.
Home-page: http://pyviz.org
Author: PyViz developers
Author-email: developers@pyviz.org
Maintainer: PyViz developers
Maintainer-email: developers@pyviz.org
License: BSD 3-Clause License
Project-URL: Bug Tracker, https://github.com/pyviz/pyviz/issues
Project-URL: Documentation, http://pyviz.org
Project-URL: Source Code, https://github.com/pyviz/pyviz
Platform: UNKNOWN
Classifier: License :: OSI Approved :: BSD License
Classifier: Operating System :: OS Independent
Classifier: Programming Language :: Python
Classifier: Programming Language :: Python :: 3.6
Classifier: Development Status :: 5 - Production/Stable
Classifier: Intended Audience :: Science/Research
Classifier: Intended Audience :: Developers
Classifier: Natural Language :: English
Classifier: Topic :: Scientific/Engineering
Requires-Python: >=3.6
Requires-Dist: bokeh (>=1.2.0)
Requires-Dist: holoviews (>=1.12.3)
Requires-Dist: hvplot (>=0.4.0)
Requires-Dist: datashader (>=0.7.0)
Requires-Dist: panel (>=0.6.0)
Requires-Dist: param (>=1.9.1)
Requires-Dist: pyct[cmd] (>=0.4.6)
Requires-Dist: ipython (<=7.1.1,>=5.4.0)
Requires-Dist: numpy (>=1.16.4)
Requires-Dist: rise
Requires-Dist: dask[complete] (>=0.18.2)
Requires-Dist: notebook (>=5.5)
Requires-Dist: matplotlib (==3.0.3)
Requires-Dist: pandas (<0.25.0,>=0.23.4)
Requires-Dist: xarray (<0.12,>=0.11.0)
Requires-Dist: streamz
Requires-Dist: netcdf4
Requires-Dist: fastparquet (>=0.2.1)
Requires-Dist: selenium
Requires-Dist: ipywidgets
Provides-Extra: doc
Requires-Dist: nbsite (>=0.5.1) ; extra == 'doc'
Requires-Dist: sphinx-pyviz-theme ; extra == 'doc'
Provides-Extra: geo
Requires-Dist: cartopy ; extra == 'geo'
Requires-Dist: geopandas ; extra == 'geo'
Requires-Dist: geoviews (>=1.6.2) ; extra == 'geo'
Provides-Extra: graphs
Requires-Dist: networkx ; extra == 'graphs'
Requires-Dist: scikit-image ; extra == 'graphs'
Provides-Extra: indirect
Requires-Dist: phantomjs ; extra == 'indirect'
Requires-Dist: python-snappy ; extra == 'indirect'
Requires-Dist: cffi ; extra == 'indirect'
Requires-Dist: python ; extra == 'indirect'
Provides-Extra: tests
Requires-Dist: nbsmoke (>=0.2.6) ; extra == 'tests'
Requires-Dist: flake8 ; extra == 'tests'
Requires-Dist: pytest (>=2.8.5) ; extra == 'tests'
